{
    "curriculum": {
      "authorization": "Autorizzo il trattamento dei dati personali contenuti nel mio curriculum vitae in base all’art. 13 del D. Lgs. 196/2003 e all’art. 13 GDPR 679/16.",
      "authorization-en": "I authorize the processing of personal data contained in my curriculum vitae based on art. 13 of Legislative Decree no. 196/2003 and art. 13 GDPR 679/16.",
      "date": "24/01/2024",
      "image": "https://firebasestorage.googleapis.com/v0/b/simone-failla.appspot.com/o/profile-cv.png?alt=media&token=a7730d65-2c1f-403a-bcbf-ebee3978ba92",
      "image-width": "800",
      "informations": {
        "address": "via Goya 2A, 56017, PI, Italia",
        "birth": "21/05/1994",
        "email": "simonefailla@icloud.com",
        "linkedin": "https://www.linkedin.com/in/simone-failla/",
        "phone": "+39 3519782021",
        "website": "https://simone-failla.web.app/home"
      },
      "languages": {
        "english": {
          "comprension": {
            "listen": "B1",
            "read": "B2"
          },
          "speaking": {
            "interaction": "B1",
            "oral": "B1"
          },
          "write": "B2"
        },
        "italian": "madre lingua",
        "italian-en": "native language"
      },
      "location": "Pisa",
      "other": {
        "driving_license": "B, automunito",
        "driving_license-en": "B, self-employed",
        "learning": {
          "0": "F.a.d. formazione generale volontario/lavoratore: D.P.I.; rischi e incidenti sul lavoro",
          "1": "F.a.d. sicurezza e salute in ambito sociale/sanitario: salute e sicurezza sul lavoro",
          "0-en": "F.a.d. general volunteer/worker training: PPE; risks and accidents at work",
          "1-en": "F.a.d. safety and health in the social/health sector: health and safety at work"
        },
        "publications": [
          "Failla S., Martinelli M., Del Soldato A - La Digital Fingerprint; online"
        ],
        "subscriptions": {
          "0": "Iscritto al centro dell'impiego di Pisa dal 08/07/2013",
          "0-en": "Registered at the Pisa employment center since 07/08/2013"
        }
      },
      "skills": {
        "comunication": {
          "0": "Trasparenza e diplomazia in un linguaggio informale e fluente",
          "1": "Buona attitudine alla comunicazione telematica",
          "0-en": "Transparency and diplomacy in an informal and fluent language",
          "1-en": "Good aptitude for telematic communication"
        },
        "digital": {
          "0": "Gestione siti web tramite CMS",
          "1": "Produzione di documentazione tecnica con Markdown",
          "2": "Gestione social media, anche tramite Postpickr",
          "3": "Progettazione grafica di base con Photoshop e Illustrator",
          "4": "UX/UI design con Adobe XD",
          "5": "Linguaggi, tools e framework usati per progetti universitari e lavoro: HTML, CSS,/SCSS Javascript, Python, XML, XSL, PHP, MySql, Vue, Django, Boostrap, Angular,  Tailwind, NLTK e Nuxt.",
          "0-en": "Website management via CMS",
          "1-en": "Production of technical documentation with Markdown",
          "2-en": "Social media management, also via Postpickr",
          "3-en": "Basic graphic design with Photoshop and Illustrator",
          "4-en": "UX/UI design with Adobe XD",
          "5-en": "Languages, tools and frameworks used for university and work projects: HTML, CSS,/SCSS Javascript, Python, XML, XSL, PHP, MySql, Vue, Django, Boostrap, Angular, Tailwind, NLTK and Nuxt."
        },
        "management": {
          "0": "Perseguire obiettivi confrontandomi con il cliente/datore di lavoro passo per passo rispettando il più possibile i tempi previsti",
          "0-en": "Pursue objectives by comparing myself with the client/employer step by step, respecting the expected timescales as much as possible"
        },
        "professional": {
          "0": "Fotografia, progettazione e programmazione web",
          "0-en": "Photography, web design and programming"
        }
      },
      "training": [
        {
          "dates": "05/02/2021 - 15/03/2022",
          "description": {
            "0": "Digital Forensics, GDPR, network security & social hacking, applied cryptography, cyber intelligence, operating system security.",
            "0-en": "Digital Forensics, GDPR, network security & social hacking, applied cryptography, cyber intelligence, operating system security."
          },
          "istitute": "università di Pisa",
          "istitute-en": "University of Pisa",
          "title": "MASTER 1° LIVELLO IN CYBERSECURITY",
          "title-en": "1ST LEVEL MASTER IN CYBERSECURITY"
        },
        {
          "dates": "25/09/2017 - 04/06/2020",
          "description": {
            "0": "Sviluppo web, produzione multimediale, discipline umanistiche",
            "1": "Tesi sperimentale sull’importanza dei contenuti di Instagram nel teatro moderno italiano; usando programmi scritti in Python ed espressioni regolari per l’analisi testuali e delle immagini, Instaloader, NLTK e DyLan. ",
            "0-en": "Web development, multimedia production, humanities",
            "1-en": "Experimental thesis on the importance of Instagram content in modern Italian theatre; using programs written in Python and regular expressions for text and image analysis, Instaloader, NLTK and DyLan."
          },
          "istitute": "università di Pisa",
          "istitute-en": "University of Pisa",
          "title": "LAUREA TRIENNALE IN INFORMATICA UMANISTICA",
          "title-en": "BACHELOR'S DEGREE IN DIGITAL HUMANITIES"
        },
        {
          "dates": "Giugno 2016",
          "description": {
            "0": "Computer and online essentials, online essentials, IT security, M. office",
            "0-en": "Computer and online essentials, online essentials, IT security, M. office"
          },
          "istitute": "associazione AICA",
          "istitute-en": "AICA association",
          "title": "ECDL STANDARD",
          "title-en": "ECDL STANDARD"
        },
        {
          "dates": "04/07/2013",
          "description": {
            "0": "Estimo, topografia, disegno tecnico, impianti",
            "0-en": "Estimate, topography, technical drawing, systems"
          },
          "istitute": "I.T.G. E. Santoni, Pisa",
          "istitute-en": "I.T.G. E. Santoni, Pisa",
          "title": "DIPLOMA DI GEOMETRA",
          "title-en": "SURVEYOR'S DIPLOMA"
        }
      ],
      "white-space-en": "10rem",
      "white_space": "10rem",
      "works": [
        {
          "agency": "ITmind s.r.l.",
          "contract": "apprendistato",
          "contract-en": "apprenticeship",
          "date": "01/09/2022 - ad ora",
          "description": {
            "0": "Linguaggi: Typescript, Javascript, CSS/SCSS, HTML, Dart, Markdown",
            "1": "Framework: Vue 3, Nuxt 3, Flutter, Bootstrap 5, Tailwind, October CMS",
            "2": "Sviluppo interfacce grafiche, siti web e documentazione tecnica",
            "3": "UX/UI design con Adobe Photoshop e Adobe XD ",
            "0-en": "Languages: Typescript, Javascript, CSS/SCSS, HTML, Dart, Markdown",
            "1-en": "Frameworks: Vue 3, Nuxt 3, Flutter, Bootstrap 5, Tailwind, October CMS",
            "2-en": "Development of graphic interfaces, websites and technical documentation",
            "3-en": "UX/UI design with Adobe Photoshop and Adobe XD"
          },
          "location": "Lucca",
          "title": "WEB E MOBILE DEVELOPER",
          "title-en": "WEB AND MOBILE DEVELOPER"
        },
        {
          "agency": "Sinergystudio s.r.l.",
          "contract": "apprendistato",
          "contract-en": "apprenticeship",
          "date": "01/08/2021 - 24/05/2022",
          "description": {
            "0": "Linguaggi: Typescript, Javascript, CSS/SCSS, HTML, C#",
            "1": "Framework: Angular 12, .NET 5",
            "2": "Sviluppo, versionamento con Git, testing e debug",
            "3": "Interventi grafici e uso delle flexbox tramite CSS e HTML",
            "0-en": "Languages: Typescript, Javascript, CSS/SCSS, HTML, C#",
            "1-en": "Frameworks: Angular 12, .NET 5",
            "2-en": "Development, versioning with Git, testing and debugging",
            "3-en": "Graphic interventions and use of flexboxes via CSS and HTML"
          },
          "location": "Pisa",
          "title": "SOFTWARE DEVELOPER",
          "title-en": "SOFTWARE DEVELOPER"
        },
        {
          "agency": "Hibo s.r.l.",
          "contract": "stage",
          "contract-en": "internship",
          "date": "01/07/2020 - 31/12/2020",
          "description": {
            "0": "Creazione pagine web da back-end mediante Drupal e Typo3",
            "1": "Inserimento CSS e HTML, testing e debug di siti web",
            "2": "Post-produzione di foto mediante Photoshop",
            "0-en": "Creation of web pages from back-end using Drupal and Typo3",
            "1-en": "CSS and HTML insertion, testing and debugging of websites",
            "2-en": "Post-production of photos using Photoshop"
          },
          "location": "Bologna",
          "title": "WEB DEVELOPER",
          "title-en": "WEB DEVELOPER"
        },
        {
          "agency": "Ente Culturale Azul Teatro",
          "contract": "tirocinio curriculare",
          "contract-en": "curricular internship",
          "date": "29/10/2019 - 05/01/2020",
          "description": {
            "0": "Gestione social media: progettazione e programmazione di contenuti, pubblicazioni ed eventi su Linkedin, Instagram, Facebook e Twitter",
            "1": "Foto di scenografia, performance, backstage e pubblico",
            "0-en": "Social media management: design and programming of content, publications and events on Linkedin, Instagram, Facebook and Twitter",
            "1-en": "Photos of scenography, performance, backstage and audience"
          },
          "location": "Lucca",
          "title": "SOCIAL MEDIA MANAGER",
          "title-en": "SOCIAL MEDIA MANAGER"
        }
      ]
    }
  }